commons_1c/__about__.py
commons_1c/__init__.py
commons_1c/platform_.py
commons_1c/version.py
tests/__init__.py
tests/test_commons_1c.py
commons_1c-3.7.3.dist-info/METADATA
commons_1c-3.7.3.dist-info/WHEEL
commons_1c-3.7.3.dist-info/top_level.txt
commons_1c-3.7.3.dist-info/RECORD
