Metadata-Version: 2.4
Name: commons-1c
Version: 3.7.3
Summary: Commons for 1C:Enterprise
Author-email: Cujoko <cujoko@gmail.com>
License: MIT
Project-URL: repository, https://github.com/Cujoko-Dev/commons-1c
Keywords: 1c,commons
Classifier: Development Status :: 5 - Production/Stable
Classifier: Intended Audience :: Developers
Classifier: License :: OSI Approved :: MIT License
Classifier: Natural Language :: Russian
Classifier: Programming Language :: Python :: 3.14
Classifier: Programming Language :: Python :: 3.13
Classifier: Programming Language :: Python :: 3.12
Classifier: Programming Language :: Python :: 3.11
Classifier: Programming Language :: Python :: 3.10
Classifier: Topic :: Software Development
Classifier: Topic :: Utilities
Requires-Python: >=3.10
Requires-Dist: appdirs>=1.4.4
Requires-Dist: cjk-commons<4.0.0,>=3.6.3
Requires-Dist: loguru>=0.6.0
